catecs/__init__.py
catecs/core.py
catecs-0.1.2.dist-info/DESCRIPTION.rst
catecs-0.1.2.dist-info/METADATA
catecs-0.1.2.dist-info/RECORD
catecs-0.1.2.dist-info/WHEEL
catecs-0.1.2.dist-info/metadata.json
catecs-0.1.2.dist-info/top_level.txt
