Metadata-Version: 2.0
Name: catecs
Version: 0.1.2
Summary: A categorical entity component system
Home-page: https://github.com/RikHendriks/catecs
Author: Rik Hendriks
Author-email: rikhendriks@rocketmail.com
License: MIT License
